README.md
setup.cfg
setup.py
rectpack/__init__.py
rectpack/enclose.py
rectpack/geometry.py
rectpack/guillotine.py
rectpack/maxrects.py
rectpack/pack_algo.py
rectpack/packer.py
rectpack/skyline.py
rectpack/waste.py
rectpack.egg-info/PKG-INFO
rectpack.egg-info/SOURCES.txt
rectpack.egg-info/dependency_links.txt
rectpack.egg-info/not-zip-safe
rectpack.egg-info/requires.txt
rectpack.egg-info/top_level.txt