Metadata-Version: 1.1
Name: rectpack
Version: 0.2.1
Summary: A collection of heuristic algorithms for solving the 2D knapsack problem,
Home-page: https://github.com/secnot/rectpack/
Author: SecNot
Author-email: UNKNOWN
License: GPLv2
Keywords: knapsack,rectangle,packing 2D,bin,binpacking
Platform: UNKNOWN
Classifier: Development Status :: 3 - Alpha
Classifier: Programming Language :: Python
Classifier: Programming Language :: Python :: 3
Classifier: License :: OSI Approved :: Apache Software License
